{"glsl.json": [
    {
        "prefix": "^[ \\t]*#[ \\t]*",
        "id": "preprocessor",
        "keyword": [
            "define",
            "undef",
            "(if|elif)([ \\t]+defined)?",
            "ifdef",
            "ifndef",
            "else",
            "endif",
            "error",
            "pragma",
            "extension",
            "version",
            "line"
        ],
        "style-ref": "preprocessor"
    },
    {
        "id": "common-macros",
        "keyword": [
            "__VERSION__",
            "__LINE__",
            "__FILE__"
        ],
        "style-ref": "preprocessor"
    },
    {
        "id": "keywords",
        "keyword": [
            "break",
            "continue",
            "discard",
            "do",
            "for",
            "if",
            "else",
            "return",
            "while",
            "switch",
            "case",
            "default",
            "attribute",
            "const",
            "in",
            "inout",
            "out",
            "uniform",
            "varying",
            "invariant",
            "centroid",
            "flat",
            "smooth",
            "noperspective",
            "layout",
            "patch",
            "sample",
            "subroutine",
            "lowp",
            "mediump",
            "highp",
            "precision"
        ],
        "style-ref": "keyword"
    },
    {
        "id": "primitives",
        "keyword": [
            "bool",
            "float",
            "double",
            "int",
            "uint",
            "struct",
            "void",
            "[bdiu]?vec[2-4]",
            "[d]?mat[2-4]",
            "[d]?mat[2-4]x[2-4]",
            "[iu]?sampler[1-3]D",
            "sampler[1-2]DShadow",
            "[iu]?sampler[1-2]DArray",
            "sampler[1-2]DArrayShadow",
            "[iu]?samplerCube",
            "samplerCubeShadow",
            "[iu]?sampler2DRect",
            "sampler2DRectShadow",
            "[iu]?samplerBuffer",
            "[iu]?sampler2DMS",
            "[iu]?sampler2DMSArray",
            "[iu]?sampler2DMSCubeArray",
            "samplerCubeArrayShadow"
        ],
        "style-ref": "type"
    },
    {
        "id": "reserved-keywords-for-future-use",
        "keyword": [
            "common",
            "partition",
            "active",
            "asm",
            "class",
            "union",
            "enum",
            "typedef",
            "template",
            "this",
            "packed",
            "goto",
            "inline",
            "noinline",
            "volatile",
            "public",
            "static",
            "extern",
            "external",
            "interface",
            "long",
            "short",
            "half",
            "fixed",
            "unsigned",
            "input",
            "output",
            "[hf]vec[2-4]",
            "sampler3DRect",
            "filter",
            "sizeof",
            "cast",
            "namespace",
            "using",
            "row_major"
        ],
        "style-ref": "future-use"
    },
    {
        "id": "builtin-functions",
        "keyword": [
            "radians",
            "degrees",
            "sin",
            "cos",
            "tan",
            "asin",
            "acos",
            "atan",
            "sinh",
            "cosh",
            "tanh",
            "asinh",
            "acosh",
            "atanh",
            "pow",
            "exp",
            "log",
            "exp2",
            "log2",
            "sqrt",
            "inversesqrt",
            "abs",
            "sign",
            "floor",
            "trunc",
            "round",
            "roundEven",
            "ceil",
            "fract",
            "mod",
            "modf",
            "min",
            "max",
            "clamp",
            "mix",
            "step",
            "smoothstep",
            "isnan",
            "isinf",
            "floatBitsToInt",
            "floatBitsToUint",
            "intBitsToFloat",
            "uintBitsToFloat",
            "fma",
            "frexp",
            "ldexp",
            "packUnorm2x16",
            "packUnorm4x8",
            "packSnorm4x8",
            "unpackUnorm2x16",
            "unpackUnorm4x8",
            "unpackSnorm4x8",
            "packDouble2x32",
            "unpackDouble2x32",
            "length",
            "distance",
            "dot",
            "cross",
            "normalize",
            "ftransform",
            "faceforward",
            "reflect",
            "refract",
            "matrixCompMult",
            "outerProduct",
            "transpose",
            "determinant",
            "inverse",
            "lessThan",
            "lessThanEqual",
            "greaterThan",
            "greaterThanEqual",
            "equal",
            "notEqual",
            "any",
            "all",
            "not",
            "uaddCarry",
            "usubBorrow",
            "umulExtended",
            "imulExtended",
            "bitfieldExtract",
            "bitfildInsert",
            "bitfieldReverse",
            "bitCount",
            "findLSB",
            "findMSB",
            "textureSize",
            "textureQueryLOD",
            "texture",
            "textureProj",
            "textureLod",
            "textureOffset",
            "texelFetch",
            "texelFetchOffset",
            "textureProjOffset",
            "textureLodOffset",
            "textureProjLod",
            "textureProjLodOffset",
            "textureGrad",
            "textureGradOffset",
            "textureProjGrad",
            "textureProjGradOffset",
            "textureGather",
            "textureGatherOffset",
            "texture[1-3]D",
            "texture[1-3]DProj",
            "texture[1-3]DLod",
            "texture[1-3]DProjLod",
            "textureCube",
            "textureCubeLod",
            "shadow[1-2]D",
            "shadow[1-2]DProj",
            "shadow[1-2]DLod",
            "shadow[1-2]DProjLod",
            "dFdx",
            "dFdy",
            "fwidth",
            "interpolateAtCentroid",
            "interpolateAtSample",
            "interpolateAtOffset",
            "noise[1-4]",
            "EmitStreamVertex",
            "EndStreamPrimitive",
            "EmitVertex",
            "EndPrimitive",
            "barrier"
        ],
        "style-ref": "builtin-function"
    },
    {
        "id": "builtin-variables",
        "keyword": [
            "gl_VertexID",
            "gl_InstanceID",
            "gl_Position",
            "gl_PointSize",
            "gl_ClipDistance",
            "gl_PrimitiveIDIn",
            "gl_InvocationID",
            "gl_PrimitiveID",
            "gl_Layer",
            "gl_PatchVerticesIn",
            "gl_TessLevelOuter",
            "gl_TessLevelInner",
            "gl_TessCoord",
            "gl_FragCoord",
            "gl_FrontFacing",
            "gl_PointCoord",
            "gl_SampleID",
            "gl_SamplePosition",
            "gl_FragColor",
            "gl_FragData",
            "gl_FragDepth",
            "gl_SampleMask",
            "gl_ClipVertex",
            "gl_FrontColor",
            "gl_BackColor",
            "gl_FrontSecondaryColor",
            "gl_BackSecondaryColor",
            "gl_TexCoord",
            "gl_FogFragCoord",
            "gl_Color",
            "gl_SecondaryColor",
            "gl_Normal",
            "gl_Vertex",
            "gl_MultiTexCoord[0-7]",
            "gl_FogCoord"
        ],
        "style-ref": "builtin-variable"
    },
    {
        "id": "builtin-constants",
        "keyword": [
            "gl_MaxVertexAttribs",
            "gl_MaxVertexUniformComponents",
            "gl_MaxVaryingFloats",
            "gl_MaxVaryingComponents",
            "gl_MaxVertexOutputComponents",
            "gl_MaxGeometryInputComponents",
            "gl_MaxGeometryOutputComponents",
            "gl_MaxFragmentInputComponents",
            "gl_MaxVertexTextureImageUnits",
            "gl_MaxCombinedTextureImageUnits",
            "gl_MaxTextureImageUnits",
            "gl_MaxFragmentUniformComponents",
            "gl_MaxDrawBuffers",
            "gl_MaxClipDistances",
            "gl_MaxGeometryTextureImageUnits",
            "gl_MaxGeometryOutputVertices",
            "gl_MaxGeometryTotalOutputComponents",
            "gl_MaxGeometryUniformComponents",
            "gl_MaxGeometryVaryingComponents",
            "gl_MaxTessControlInputComponents",
            "gl_MaxTessControlOutputComponents",
            "gl_MaxTessControlTextureImageUnits",
            "gl_MaxTessControlUniformComponents",
            "gl_MaxTessControlTotalOutputComponents",
            "gl_MaxTessEvaluationInputComponents",
            "gl_MaxTessEvaluationOutputComponents",
            "gl_MaxTessEvaluationTextureImageUnits",
            "gl_MaxTessEvaluationUniformComponents",
            "gl_MaxTessPatchComponents",
            "gl_MaxPatchVertices",
            "gl_MaxTessGenLevel",
            "gl_MaxTextureUnits",
            "gl_MaxTextureCoords",
            "gl_MaxClipPlanes"
        ],
        "style-ref": "builtin-constant"
    },
    {
        "id": "builtin-uniform-states",
        "keyword": [
            "gl_DepthRange",
            "gl_ModelViewMatrix",
            "gl_ProjectionMatrix",
            "gl_ModelViewProjectionMatrix",
            "gl_TextureMatrix",
            "gl_NormalMatrix",
            "gl_ModelViewMatrixInverse",
            "gl_ProjectionMatrixInverse",
            "gl_ModelViewProjectionMatrixInverse",
            "gl_TextureMatrixInverse",
            "gl_ModelViewMatrixTranspose",
            "gl_ProjectionMatrixTranspose",
            "gl_ModelViewProjectionMatrixTranspose",
            "gl_TextureMatrixTranspose",
            "gl_ModelViewMatrixInverseTranspose",
            "gl_ProjectionMatrixInverseTranspose",
            "gl_ModelViewProjectionMatrixInverseTranspose",
            "gl_TextureMatrixInverseTranspose",
            "gl_NormalScale",
            "gl_ClipPlane",
            "gl_Point",
            "gl_FrontMaterial",
            "gl_BackMaterial",
            "gl_LightSource",
            "gl_LightModel",
            "gl_FrontLightModelProduct",
            "gl_BackLightModelProduct",
            "gl_FrontLightProduct",
            "gl_BackLightProduct",
            "gl_TextureEnvColor",
            "gl_EyePlaneS",
            "gl_EyePlaneT",
            "gl_EyePlaneR",
            "gl_EyePlaneQ",
            "gl_ObjectPlaneS",
            "gl_ObjectPlaneT",
            "gl_ObjectPlaneR",
            "gl_ObjectPlaneQ",
            "gl_Fog"
        ],
        "style-ref": "builtin-constant"
    },
    {
        "include": {"context": [
            {"ref": "def:c-like-comment"},
            {"ref": "def:c-like-comment-multiline"},
            {"ref": "def:c-like-close-comment-outside-comment"},
            {"ref": "c:if0-comment"},
            {"ref": "preprocessor"},
            {"ref": "common-macros"},
            {"ref": "keywords"},
            {"ref": "primitives"},
            {"ref": "c:boolean"},
            {"ref": "c:decimal"},
            {"ref": "c:octal"},
            {"ref": "c:hexadecimal"},
            {"ref": "c:float"},
            {"ref": "builtin-functions"},
            {"ref": "builtin-variables"},
            {"ref": "builtin-constants"},
            {"ref": "builtin-uniform-states"},
            {"ref": "reserved-keywords-for-future-use"}
        ]},
        "id": "glsl"
    }
]}